README.md
setup.py
linalg/__init__.py
linalg/create.py
linalg/data.py
linalg/decompose.py
linalg/solve.py
linalg/types.py
linalg/unary.py
linalg.egg-info/PKG-INFO
linalg.egg-info/SOURCES.txt
linalg.egg-info/dependency_links.txt
linalg.egg-info/top_level.txt