Metadata-Version: 2.1
Name: linalg
Version: 1.0.3
Summary: A simple linear algebra package written in vanilla python3
Home-page: https://github.com/rocketll/linalg
Author: Lucas Lee
Author-email: luc4sl33@gmail.com
License: MIT
Keywords: linear algebra,math
Platform: UNKNOWN
Requires-Python: >=3.6.0
